datastore/__init__.py
datastore/datastorereq.py
datastore/exceptions.py
datastore/imports.py
rodatabase.py-1.0.3.dist-info/LICENSE
rodatabase.py-1.0.3.dist-info/METADATA
rodatabase.py-1.0.3.dist-info/WHEEL
rodatabase.py-1.0.3.dist-info/top_level.txt
rodatabase.py-1.0.3.dist-info/RECORD
